streamlit_bookmark/__init__.py
streamlit_bookmark/frontend/build/asset-manifest.json
streamlit_bookmark/frontend/build/bootstrap.min.css
streamlit_bookmark/frontend/build/index.html
streamlit_bookmark/frontend/build/static/js/main.e94766ac.js
streamlit_bookmark/frontend/build/static/js/main.e94766ac.js.LICENSE.txt
streamlit_bookmark/frontend/build/static/js/main.e94766ac.js.map
streamlit_bookmark-0.1.2.dist-info/LICENSE
streamlit_bookmark-0.1.2.dist-info/METADATA
streamlit_bookmark-0.1.2.dist-info/WHEEL
streamlit_bookmark-0.1.2.dist-info/top_level.txt
streamlit_bookmark-0.1.2.dist-info/RECORD
