Metadata-Version: 2.1
Name: streamlit-bookmark
Version: 0.1.2
Summary: Streamlit component that allows you to bookmark chat messages in your apps
Home-page: https://github.com/parsa-asgari/streamlit-bookmark
Author: Parsa Asgari
Author-email: parsa.asgari3264@gmail.com
Requires-Python: >=3.7
License-File: LICENSE
Requires-Dist: streamlit >=0.63
